isnippet/__init__.py
isnippet/py.typed
isnippet-0.1.0.dev0.dist-info/METADATA
isnippet-0.1.0.dev0.dist-info/WHEEL
isnippet-0.1.0.dev0.dist-info/RECORD
