Metadata-Version: 2.4
Name: isnippet
Version: 0.1.0.dev0
Summary: Add your description here
Author-email: alaamer12 <ahmedmuhmmed239@gmail.com>
Requires-Python: >=3.11
